MANIFEST.in
readme.md
setup.py
auto_artifacts/__init__.py
auto_artifacts.egg-info/PKG-INFO
auto_artifacts.egg-info/SOURCES.txt
auto_artifacts.egg-info/dependency_links.txt
auto_artifacts.egg-info/requires.txt
auto_artifacts.egg-info/top_level.txt
auto_artifacts/client/__init__.py
auto_artifacts/client/artifact.py
auto_artifacts/server/__init__.py
auto_artifacts/server/api_download.py
auto_artifacts/server/api_health.py
auto_artifacts/server/api_keys.py
auto_artifacts/server/api_list.py
auto_artifacts/server/api_upload.py
auto_artifacts/server/app.py
auto_artifacts/server/config.py
tests/__init__.py
tests/test_auto_artifacts_admin.py
tests/test_auto_artifacts_dev.py
tests/test_auto_artifacts_machine.py
tests/test_auto_artifacts_viewer.py
tests/utils.py