Metadata-Version: 2.1
Name: auto-artifacts
Version: 2024.3.12
Summary: Simple service to manage your artifacts
Home-page: https://github.com/veda-s4dhak/auto-artifacts.git
Author: Veda Sadhak
Author-email: vedasadhak@gmail.com
License: UNKNOWN
Platform: UNKNOWN
Classifier: Development Status :: 3 - Alpha
Classifier: Intended Audience :: Developers
Classifier: Natural Language :: English
Classifier: License :: OSI Approved :: MIT License
Classifier: Operating System :: OS Independent
Classifier: Programming Language :: Python :: 3
Classifier: Programming Language :: Python :: 3.7
Classifier: Programming Language :: Python :: 3.8
Classifier: Programming Language :: Python :: 3.9
Classifier: Programming Language :: Python :: 3.10
Requires-Python: >=3.7
